pcsbFocus/__init__.py
pcsbFocus/focus.py
pcsbFocus-0.0.1.dist-info/LICENSE
pcsbFocus-0.0.1.dist-info/METADATA
pcsbFocus-0.0.1.dist-info/WHEEL
pcsbFocus-0.0.1.dist-info/top_level.txt
pcsbFocus-0.0.1.dist-info/RECORD
