Metadata-Version: 2.1
Name: pcsbFocus
Version: 0.0.1
Summary: PCSB Focus Package
Home-page: UNKNOWN
Author: Aidan Bruner
Author-email: Aidanbruner789@gmail.com
License: UNKNOWN
Keywords: pcsb,PCSB,student,Focus
Platform: UNKNOWN
Classifier: Development Status :: 3 - Alpha
Classifier: Intended Audience :: Education
Classifier: Programming Language :: Python :: 3
Classifier: Operating System :: POSIX :: Linux
Classifier: Operating System :: Microsoft :: Windows
License-File: LICENSE
Requires-Dist: selenium
